<chart>
	<chartSeries>
		<series>
			<name>Sales</name>
			<dbCol>otherCol</dbCol>
			<description>Number Sales</description>
			<axis>0</axis>
		</series>
		<series>
			<name>Sales1</name>
			<dbCol>noSales</dbCol>
			<description>Number Sales1</description>
			<axis>0</axis>
		</series>
	</chartSeries>
	<axes>
		<axis>
			<number>0</number>
			<name>otherCol</name>
			<unit>CDs</unit>
			<position>AXIS_POSITION_LEFT</position>
		</axis>
	</axes>
	<image>
		<xSize>700</xSize>
		<ySize>250</ySize>
		<graphArea>
			<x1></x1>
			<x2></x2>
			<y1></y1>
			<y2></y2>
		</graphArea>
		
	</image>
	<legend>
		<xPos>563</xPos>
		<yPos>16</yPos>
	</legend>
	<abscissa>
		<name>Month</name>
		<dbCol>month</dbCol>
	</abscissa>
	<chartName>Sales over Time</chartName>
	<chartType>Spline</chartType>
	<sqlQuery>
		<columns>
			<column>otherCol</column>
			<column>month</column>
			<column>noSales</column>
		</columns>
		<tables>
			<table>sales</table>
		</tables>
	</sqlQuery>
	<title>
		<name>My first pChart project</name>
		<xPos>350</xPos>
		<yPos>25</yPos>
		<rColour>0</rColour>
		<gColour>0</gColour>
		<bColour>0</bColour>
		<align>TEXT_ALIGN_MIDDLEMIDDLE</align>
		<fontName>Forgotte.ttf</fontName>
		<fontSize>14</fontSize>
	</title>
	<background>
		<rColour>170</rColour>
		<gColour>183</gColour>
		<bColour>87</bColour>
		<dash>1</dash><!-- 1 or 0 (off) -->
		<rColourDash>190</rColourDash>
		<gColourDash>203</gColourDash>
		<bColourDash>107</bColourDash>
		<gradient>
			<on>1</on><!-- 1 or 0 (off) -->
			<startRColour>219</startRColour>
			<startGColour>231</startGColour>
			<startBColour>139</startBColour>
			<endRColour>1</endRColour>
			<endGColour>138</endGColour>
			<endBColour>68</endBColour>
			<transparency>50</transparency> <!-- between 0 and 100% -->
			<direction>DIRECTION_VERTICAL</direction>
		</gradient>
	</background>
</chart>